bids_events/Events.py
bids_events/__init__.py
bids_events/presentation.py
bids_events-0.0.5.dist-info/METADATA
bids_events-0.0.5.dist-info/RECORD
bids_events-0.0.5.dist-info/WHEEL
bids_events-0.0.5.dist-info/top_level.txt
