Metadata-Version: 2.1
Name: bids-events
Version: 0.0.5
Summary: A package to export events to be used in BIDS datasets.
Home-page: https://github.com/InstitutoDOr/bids_events
Author: Bruno Melo
Author-email: bruno.melo@idor.org
License: UNKNOWN
Platform: UNKNOWN
Classifier: Programming Language :: Python :: 2
Classifier: License :: OSI Approved :: MIT License
Classifier: Operating System :: OS Independent
